ream/__init__.py
ream/__main__.py
ream/_convert.py
ream/commandline.py
ream/decode.py
ream/encode.py
ream/grammar.py
ream/transformer.py
ream-0.1.3.4.dist-info/entry_points.txt
ream-0.1.3.4.dist-info/LICENSE
ream-0.1.3.4.dist-info/WHEEL
ream-0.1.3.4.dist-info/METADATA
ream-0.1.3.4.dist-info/RECORD
